anygrate
