Metadata-Version: 1.0
Name: anybox.migration.openerp
Version: 0.8
Summary: Fast OpenERP migration framework
Home-page: https://bitbucket.org/anybox/anybox.migration.openerp/overview
Author: Anybox
Author-email: contact@anybox.fr
License: GPLv3+
Platform: UNKNOWN
